src/__init__.py
src/__version__.py
src/auditor.py
src/logger.py
src/main.py
src/semantic_suggester.py
src/dags/__init__.py
src/dags/nber.rulebased.extractions.jsonl.nxdigraph.json
src/dags/nber_abstracts.rulebased.extractions.jsonl.nxdigraph.json
src/path_printers/__init__.py
src/path_printers/abstracts_printer.py
src/path_printers/vertex_printer.py
roboteconomist-0.4.9.dist-info/METADATA
roboteconomist-0.4.9.dist-info/WHEEL
roboteconomist-0.4.9.dist-info/entry_points.txt
roboteconomist-0.4.9.dist-info/top_level.txt
roboteconomist-0.4.9.dist-info/RECORD
